{
  "condition": "minecraft:any_of",
  "terms": [
    {
      "condition": "minecraft:entity_properties",
      "entity": "this",
      "predicate": {
        "nbt": "{'SelectedItem':{'components':{'minecraft:damage':336}}}"
      }
    },
    {
      "condition": "minecraft:entity_properties",
      "entity": "this",
      "predicate": {
        "nbt": "{'SelectedItem':{'components':{'minecraft:damage':335}}}"
      }
    },
    {
      "condition": "minecraft:entity_properties",
      "entity": "this",
      "predicate": {
        "nbt": "{'SelectedItem':{'components':{'minecraft:damage':334}}}"
      }
    }
  ]
}
