{
  "pools": [
    {
      "rolls": 1,
      "entries": [
        {
          "type": "minecraft:loot_table",
          "value": "dark_dungeons:items/food/berries/everbloom_berries",
          "weight": 99,
          "functions": [
            {
              "function": "minecraft:set_count",
              "count": {
                "type": "minecraft:uniform",
                "min": 2,
                "max": 3
              }
            }
          ]
        },
        {
          "type": "minecraft:loot_table",
          "weight": 1,
          "value": "dark_dungeons:items/food/berries/sunveil_berries"
        }
      ]
    }
  ]
}